dj_apibrowser.py
dj_apibrowser-0.2.0.dist-info/LICENSE
dj_apibrowser-0.2.0.dist-info/METADATA
dj_apibrowser-0.2.0.dist-info/WHEEL
dj_apibrowser-0.2.0.dist-info/top_level.txt
dj_apibrowser-0.2.0.dist-info/zip-safe
dj_apibrowser-0.2.0.dist-info/RECORD
