Metadata-Version: 2.1
Name: dj-apibrowser
Version: 0.2.0
Summary: Generic GUI for any RESTful API
Home-page: https://gitlab.com/LEW21/dj-apibrowser
Author: Linus Lewandowski
Author-email: linus@lew21.net
License: UNKNOWN
Keywords: rest api browser
Platform: UNKNOWN
Classifier: Development Status :: 4 - Beta
Classifier: Intended Audience :: Developers
Classifier: License :: OSI Approved :: MIT License
Classifier: Programming Language :: Python :: 3
Classifier: Programming Language :: Python :: 3 :: Only
Classifier: Programming Language :: Python :: 3.4
Classifier: Programming Language :: Python :: 3.5
Classifier: Programming Language :: Python :: 3.6
Classifier: Programming Language :: Python :: 3.7
Classifier: Framework :: Django
Classifier: Framework :: Django :: 2.0
Classifier: Framework :: Django :: 2.1
Classifier: Framework :: Django :: 2.2
